{
  "id": "3f159056-0988-445e-b47b-3215a2015908",
  "prevId": "322f2630-fae2-46cf-95a1-4004ccebb9b7",
  "version": "5",
  "dialect": "pg",
  "tables": {
    "businesses": {
      "name": "businesses",
      "schema": "",
      "columns": {
        "id": {
          "name": "id",
          "type": "uuid",
          "primaryKey": true,
          "notNull": true,
          "default": "gen_random_uuid()"
        },
        "title": {
          "name": "title",
          "type": "text",
          "primaryKey": false,
          "notNull": true
        },
        "created_at": {
          "name": "created_at",
          "type": "timestamp with time zone",
          "primaryKey": false,
          "notNull": true,
          "default": "now()"
        },
        "created_by": {
          "name": "created_by",
          "type": "uuid",
          "primaryKey": false,
          "notNull": true
        }
      },
      "indexes": {},
      "foreignKeys": {
        "businesses_created_by_users_id_fk": {
          "name": "businesses_created_by_users_id_fk",
          "tableFrom": "businesses",
          "tableTo": "users",
          "columnsFrom": [
            "created_by"
          ],
          "columnsTo": [
            "id"
          ],
          "onDelete": "cascade",
          "onUpdate": "no action"
        }
      },
      "compositePrimaryKeys": {},
      "uniqueConstraints": {}
    },
    "users": {
      "name": "users",
      "schema": "",
      "columns": {
        "id": {
          "name": "id",
          "type": "uuid",
          "primaryKey": true,
          "notNull": true
        },
        "email": {
          "name": "email",
          "type": "text",
          "primaryKey": false,
          "notNull": false
        },
        "created_at": {
          "name": "created_at",
          "type": "timestamp with time zone",
          "primaryKey": false,
          "notNull": true,
          "default": "now()"
        }
      },
      "indexes": {},
      "foreignKeys": {},
      "compositePrimaryKeys": {},
      "uniqueConstraints": {}
    }
  },
  "enums": {},
  "schemas": {},
  "_meta": {
    "schemas": {},
    "tables": {},
    "columns": {}
  }
}